<?xml version="1.0" encoding="utf-8"?>
<script>
<v t="n" n="__sys__t400">239</v>
<v t="n" n="__sys__t391">233</v>
<v t="n" n="__sys__t329">198</v>
<v t="n" n="__sys__t328">198</v>
<v t="n" n="__sys__t326">197</v>
<v t="n" n="__sys__t316">188</v>
<v t="n" n="__sys__t304">179</v>
<v t="n" n="__sys__t303">179</v>
<v t="n" n="__sys__t251">144</v>
<v t="n" n="__sys__t248">142</v>
<v t="n" n="__sys__t247">142</v>
<v t="n" n="__sys__t245">141</v>
<v t="n" n="__sys__t244">141</v>
<v t="n" n="__sys__t206">110</v>
<v t="n" n="__sys__t180">93</v>
<v t="n" n="__sys__t179">93</v>
<v t="n" n="__sys__t178">93</v>
<v t="n" n="__sys__t176">92</v>
<v t="n" n="__sys__t174">91</v>
<v t="n" n="__sys__t145">65</v>
<v t="n" n="__sys__t143">64</v>
<v t="n" n="__sys__t136">60</v>
<v t="n" n="__sys__t1">0</v>
<v t="n" n="__sys__t2">1</v>
<v t="s" n="__sys__t3">.methodName.</v>
<v t="s" n="__sys__t4">.sessionID.</v>
<v t="n" n="__sys__t5">1000</v>
<v t="n" n="__sys__t6">0</v>
<v t="s" n="__sys__t7">.level.</v>
<v t="s" n="__sys__t8">.ERP3max.</v>
<v t="n" n="__sys__t9">0</v>
<v t="n" n="__sys__t10">0</v>
<v t="n" n="__sys__t11">1</v>
<v t="n" n="__sys__t12">0</v>
<v t="n" n="__sys__t13">1</v>
<v t="n" n="__sys__t14">0</v>
<v t="n" n="__sys__t15">0</v>
<v t="n" n="__sys__t16">0</v>
<v t="n" n="__sys__t17">1</v>
<v t="n" n="__sys__t18">1</v>
<v t="n" n="__sys__t19">0</v>
<v t="n" n="__sys__t20">0</v>
<v t="n" n="__sys__t21">0</v>
<v t="n" n="__sys__t22">0</v>
<v t="n" n="__sys__t23">0</v>
<v t="n" n="__sys__t24">0</v>
<v t="n" n="__sys__t25">0</v>
<v t="n" n="__sys__t26">0</v>
<v t="n" n="__sys__t27">1</v>
<v t="n" n="__sys__t28">3</v>
<v t="n" n="__sys__t29">0</v>
<v t="s" n="__sys__t30">.Result.</v>
<v t="n" n="__sys__t31">3</v>
<v t="n" n="__sys__t32">0</v>
<v t="n" n="__sys__t33">10000</v>
<v t="n" n="__sys__t34">0</v>
<v t="n" n="__sys__t35">60</v>
<v t="n" n="__sys__t36">300000</v>
<v t="n" n="__sys__t37">0</v>
<v t="n" n="__sys__t38">3</v>
<v t="n" n="__sys__t39">500</v>
<v t="n" n="__sys__t40">1800</v>
<v t="n" n="__sys__t41">1</v>
<v t="n" n="__sys__t42">1</v>
<v t="n" n="__sys__t43">1</v>
<v t="s" n="__sys__t44">.Result.</v>
<v t="n" n="__sys__t45">1</v>
<v t="n" n="__sys__t46">1</v>
<v t="s" n="__sys__t47">.Result.</v>
<v t="n" n="__sys__t48">2</v>
<v t="n" n="__sys__t49">0</v>
<o n="input"><o>__sys__t50</o><i>__sys__t1</i></o>
<o n="="><o>user</o><i>__sys__t50</i></o>
<o n="input"><o>__sys__t52</o><i>__sys__t2</i></o>
<o n="="><o>game</o><i>__sys__t52</i></o>
<o n="link" r="24"><o>__sys__t54</o><i>__sys__t3</i></o>
<o n="=" r="24"><o>methodName</o><i>__sys__t54</i></o>
<o n="link" r="24"><o>__sys__t56</o><i>__sys__t4</i></o>
<o n="=" r="24"><o>sessionID</o><i>__sys__t56</i></o>
<v t="s" n="__sys__t59">.json.</v>
<o n="." r="25"><o>__sys__t58</o><i>user</i><i>__sys__t59</i></o>
<o n="json_decode" r="25"><o>__sys__t61</o><i>__sys__t58</i></o>
<o n="=" r="25"><o>json</o><i>__sys__t61</i></o>
<v t="s" n="__sys__t64">.makeSoldier.</v>
<o n="." r="26"><o>__sys__t63</o><i>json</i><i>__sys__t64</i></o>
<o n="ref" r="26"><o>__sys__t66</o><i>__sys__t63</i></o>
<o n="=" r="26"><o>makeSoldier</o><i>__sys__t66</i></o>
<v t="s" n="__sys__t69">.beginTime.</v>
<o n="." r="27"><o>__sys__t68</o><i>makeSoldier</i><i>__sys__t69</i></o>
<o n="ref" r="27"><o>__sys__t71</o><i>__sys__t68</i></o>
<o n="=" r="27"><o>beginTime</o><i>__sys__t71</i></o>
<v t="s" n="__sys__t74">.dt.</v>
<o n="." r="28"><o>__sys__t73</o><i>makeSoldier</i><i>__sys__t74</i></o>
<o n="ref" r="28"><o>__sys__t76</o><i>__sys__t73</i></o>
<o n="=" r="28"><o>dt</o><i>__sys__t76</i></o>
<o n="*" r="29"><o>__sys__t78</o><i>dt</i><i>__sys__t5</i></o>
<o n="=" r="29"><o>dt1000</o><i>__sys__t78</i></o>
<o n="=" r="30"><o>recvSign</o><i>__sys__t6</i></o>
<o n="=" r="31"><o>newBeginTime</o><i>beginTime</i></o>
<o n="time_milli" r="32"><o>__sys__t82</o></o>
<o n="=" r="32"><o>curTime</o><i>__sys__t82</i></o>
<v t="s" n="__sys__t85">.table.</v>
<o n="." r="33"><o>__sys__t84</o><i>game</i><i>__sys__t85</i></o>
<v t="s" n="__sys__t88">.level.</v>
<o n="." r="33"><o>__sys__t87</o><i>__sys__t84</i><i>__sys__t88</i></o>
<v t="s" n="__sys__t91">.getRowFromColName.</v>
<o n="." r="33"><o>__sys__t90</o><i>__sys__t87</i><i>__sys__t91</i></o>
<v t="s" n="__sys__t94">.level.</v>
<o n="." r="33"><o>__sys__t93</o><i>user</i><i>__sys__t94</i></o>
<o n="__sys__t90" r="33"><o>__sys__t96</o><i>__sys__t87</i><i>__sys__t7</i><i>__sys__t93</i></o>
<o n="=" r="33"><o>row</o><i>__sys__t96</i></o>
<v t="s" n="__sys__t99">.getValFromColName.</v>
<o n="." r="34"><o>__sys__t98</o><i>row</i><i>__sys__t99</i></o>
<o n="__sys__t98" r="34"><o>__sys__t101</o><i>row</i><i>__sys__t8</i></o>
<o n="number" r="34"><o>__sys__t102</o><i>__sys__t101</i></o>
<o n="=" r="34"><o>maxRecvCount</o><i>__sys__t102</i></o>
<v t="s" n="__sys__t105">.recvCount.</v>
<o n="." r="35"><o>__sys__t104</o><i>makeSoldier</i><i>__sys__t105</i></o>
<o n="*" r="35"><o>__sys__t107</o><i>dt1000</i><i>__sys__t104</i></o>
<o n="-" r="35"><o>__sys__t108</o><i>beginTime</i><i>__sys__t107</i></o>
<o n="=" r="35"><o>roundBeginTime</o><i>__sys__t108</i></o>
<o n="+" r="36"><o>__sys__t110</o><i>roundBeginTime</i><i>dt1000</i></o>
<o n="=" r="36"><o>roundEndTime</o><i>__sys__t110</i></o>
<v t="s" n="__sys__t113">.recvCount.</v>
<o n="." r="37"><o>__sys__t112</o><i>makeSoldier</i><i>__sys__t113</i></o>
<o n=">" r="37"><o>__sys__t115</o><i>__sys__t112</i><i>__sys__t9</i></o>
<o n="="><o>__sys__rt</o><i>__sys__t115</i></o>
<o n="=="><o>__sys__t117</o><i>__sys__rt</i><i>__sys__t10</i></o>
<o n="if_goto"><o>__sys__t118</o><i>__sys__t117</i><i>__sys__t145</i></o>
<o n="=" r="39"><o>recvSign</o><i>__sys__t11</i></o>
<v t="s" n="__sys__t121">.recvCount.</v>
<o n="." r="40"><o>__sys__t120</o><i>makeSoldier</i><i>__sys__t121</i></o>
<o n="-" r="40"><o>__sys__t123</o><i>maxRecvCount</i><i>__sys__t120</i></o>
<o n="*" r="40"><o>__sys__t124</o><i>dt1000</i><i>__sys__t123</i></o>
<o n="+" r="40"><o>__sys__t125</o><i>beginTime</i><i>__sys__t124</i></o>
<o n="=" r="40"><o>endTime</o><i>__sys__t125</i></o>
<o n="&lt;" r="41"><o>__sys__t127</o><i>curTime</i><i>endTime</i></o>
<o n="="><o>__sys__rt</o><i>__sys__t127</i></o>
<o n="=="><o>__sys__t129</o><i>__sys__rt</i><i>__sys__t12</i></o>
<o n="if_goto"><o>__sys__t130</o><i>__sys__t129</i><i>__sys__t136</i></o>
<v t="s" n="__sys__t132">.recvCount.</v>
<o n="." r="43"><o>__sys__t131</o><i>makeSoldier</i><i>__sys__t132</i></o>
<o n="--" r="43"><o>__sys__t131</o><i>__sys__t131</i></o>
<o n="goto"><o>__sys__t135</o><i>__sys__t143</i></o>
<v t="s" n="__sys__t138">.recvCount.</v>
<o n="." r="47"><o>__sys__t137</o><i>makeSoldier</i><i>__sys__t138</i></o>
<o n="-" r="47"><o>__sys__t140</o><i>maxRecvCount</i><i>__sys__t13</i></o>
<o n="=" r="47"><o>__sys__t137</o><i>__sys__t140</i></o>
<o n="=" r="48"><o>newBeginTime</o><i>curTime</i></o>
<o n="goto"><o>__sys__t144</o><i>__sys__t180</i></o>
<o n="-" r="53"><o>__sys__t146</o><i>curTime</i><i>beginTime</i></o>
<o n="/" r="53"><o>__sys__t147</o><i>__sys__t146</i><i>dt1000</i></o>
<o n="floor" r="53"><o>__sys__t148</o><i>__sys__t147</i></o>
<o n="=" r="53"><o>recvCount</o><i>__sys__t148</i></o>
<o n="limit" r="54"><o>__sys__t150</o><i>recvCount</i><i>__sys__t14</i><i>maxRecvCount</i></o>
<o n="=" r="54"><o>recvCount</o><i>__sys__t150</i></o>
<o n=">" r="55"><o>__sys__t152</o><i>recvCount</i><i>__sys__t15</i></o>
<o n="="><o>__sys__rt</o><i>__sys__t152</i></o>
<o n="=="><o>__sys__t154</o><i>__sys__rt</i><i>__sys__t16</i></o>
<o n="if_goto"><o>__sys__t155</o><i>__sys__t154</i><i>__sys__t178</i></o>
<o n="=" r="57"><o>recvSign</o><i>__sys__t17</i></o>
<v t="s" n="__sys__t158">.recvCount.</v>
<o n="." r="58"><o>__sys__t157</o><i>makeSoldier</i><i>__sys__t158</i></o>
<o n="-" r="58"><o>__sys__t160</o><i>recvCount</i><i>__sys__t18</i></o>
<o n="=" r="58"><o>__sys__t157</o><i>__sys__t160</i></o>
<o n="&lt;" r="59"><o>__sys__t162</o><i>recvCount</i><i>maxRecvCount</i></o>
<o n="="><o>__sys__rt</o><i>__sys__t162</i></o>
<o n="=="><o>__sys__t164</o><i>__sys__rt</i><i>__sys__t19</i></o>
<o n="if_goto"><o>__sys__t165</o><i>__sys__t164</i><i>__sys__t174</i></o>
<o n="-" r="61"><o>__sys__t166</o><i>curTime</i><i>beginTime</i></o>
<o n="=" r="61"><o>remainingTime</o><i>__sys__t166</i></o>
<o n="*" r="62"><o>__sys__t168</o><i>recvCount</i><i>dt1000</i></o>
<o n="-" r="62"><o>__sys__t169</o><i>curTime</i><i>remainingTime</i></o>
<o n="+" r="62"><o>__sys__t170</o><i>__sys__t169</i><i>__sys__t168</i></o>
<o n="=" r="62"><o>newCurTime</o><i>__sys__t170</i></o>
<o n="=" r="63"><o>newBeginTime</o><i>newCurTime</i></o>
<o n="goto"><o>__sys__t173</o><i>__sys__t176</i></o>
<o n="=" r="67"><o>newBeginTime</o><i>curTime</i></o>
<o n="goto"><o>__sys__t177</o><i>__sys__t179</i></o>
<o n="="><o>__sys__rt</o><i>recvSign</i></o>
<o n="=="><o>__sys__t182</o><i>__sys__rt</i><i>__sys__t20</i></o>
<o n="if_goto"><o>__sys__t183</o><i>__sys__t182</i><i>__sys__t391</i></o>
<v t="s" n="__sys__t185">.hero.</v>
<o n="." r="73"><o>__sys__t184</o><i>json</i><i>__sys__t185</i></o>
<o n="=" r="73"><o>heroArr</o><i>__sys__t184</i></o>
<v t="s" n="__sys__t189">.charm.</v>
<o n="." r="74"><o>__sys__t188</o><i>user</i><i>__sys__t189</i></o>
<o n="number" r="74"><o>__sys__t191</o><i>__sys__t188</i></o>
<o n="=" r="74"><o>charm</o><i>__sys__t191</i></o>
<o n="=" r="76"><o>point</o><i>charm</i></o>
<o n="=" r="77"><o>pointPlus</o><i>__sys__t21</i></o>
<v t="s" n="__sys__t196">.hero.</v>
<o n="." r="79"><o>__sys__t195</o><i>makeSoldier</i><i>__sys__t196</i></o>
<o n="=" r="79"><o>useHeroArr</o><i>__sys__t195</i></o>
<o n="size" r="80"><o>__sys__t199</o><i>useHeroArr</i></o>
<o n="=" r="80"><o>c</o><i>__sys__t199</i></o>
<v t="s" n="__sys__t202">.numMgr.</v>
<o n="." r="81"><o>__sys__t201</o><i>game</i><i>__sys__t202</i></o>
<o n="=" r="81"><o>numMgr</o><i>__sys__t201</i></o>
<o n="=" r="82"><o>i</o><i>__sys__t22</i></o>
<o n="&lt;" r="82"><o>__sys__t207</o><i>i</i><i>c</i></o>
<o n="="><o>__sys__rt</o><i>__sys__t207</i></o>
<o n="=="><o>__sys__t209</o><i>__sys__rt</i><i>__sys__t23</i></o>
<o n="if_goto"><o>__sys__t210</o><i>__sys__t209</i><i>__sys__t251</i></o>
<o n="[]" r="84"><o>__sys__t211</o><i>useHeroArr</i><i>i</i></o>
<o n="=" r="84"><o>info</o><i>__sys__t211</i></o>
<v t="s" n="__sys__t214">.heroIndex.</v>
<o n="." r="85"><o>__sys__t213</o><i>info</i><i>__sys__t214</i></o>
<o n="=" r="85"><o>heroIndex</o><i>__sys__t213</i></o>
<o n=">=" r="86"><o>__sys__t217</o><i>heroIndex</i><i>__sys__t24</i></o>
<o n="="><o>__sys__rt</o><i>__sys__t217</i></o>
<o n="=="><o>__sys__t219</o><i>__sys__rt</i><i>__sys__t25</i></o>
<o n="if_goto"><o>__sys__t220</o><i>__sys__t219</i><i>__sys__t247</i></o>
<v t="s" n="__sys__t222">.beginTime.</v>
<o n="." r="88"><o>__sys__t221</o><i>info</i><i>__sys__t222</i></o>
<o n="=" r="88"><o>heroBeginTime</o><i>__sys__t221</i></o>
<o n="&lt;" r="89"><o>__sys__t225</o><i>heroBeginTime</i><i>roundEndTime</i></o>
<o n="="><o>__sys__rt</o><i>__sys__t225</i></o>
<o n="=="><o>__sys__t227</o><i>__sys__rt</i><i>__sys__t26</i></o>
<o n="if_goto"><o>__sys__t228</o><i>__sys__t227</i><i>__sys__t244</i></o>
<o n="limit" r="91"><o>__sys__t229</o><i>heroBeginTime</i><i>roundBeginTime</i><i>roundEndTime</i></o>
<o n="=" r="91"><o>heroBeginTime</o><i>__sys__t229</i></o>
<o n="-" r="92"><o>__sys__t231</o><i>roundEndTime</i><i>heroBeginTime</i></o>
<o n="=" r="92"><o>useTime</o><i>__sys__t231</i></o>
<o n="/" r="93"><o>__sys__t233</o><i>useTime</i><i>dt1000</i></o>
<o n="=" r="93"><o>usePercent</o><i>__sys__t233</i></o>
<o n="[]" r="94"><o>__sys__t235</o><i>heroArr</i><i>heroIndex</i></o>
<o n="=" r="94"><o>heroInfo</o><i>__sys__t235</i></o>
<v t="s" n="__sys__t238">.charmTotal.</v>
<o n="." r="95"><o>__sys__t237</o><i>heroInfo</i><i>__sys__t238</i></o>
<o n="*" r="95"><o>__sys__t240</o><i>__sys__t237</i><i>usePercent</i></o>
<o n="floor" r="95"><o>__sys__t241</o><i>__sys__t240</i></o>
<o n="+=" r="95"><o>pointPlus</o><i>__sys__t241</i></o>
<o n="goto"><o>__sys__t243</o><i>__sys__t245</i></o>
<o n="goto"><o>__sys__t246</o><i>__sys__t248</i></o>
<o n="++" r="98"><o>i</o><i>i</i></o>
<o n="goto"><o>__sys__t250</o><i>__sys__t206</i></o>
<o n="=" r="102"><o>percent</o><i>__sys__t27</i></o>
<v t="s" n="__sys__t254">.wifePlus.</v>
<o n="." r="104"><o>__sys__t253</o><i>json</i><i>__sys__t254</i></o>
<v t="s" n="__sys__t257">.businessPercent.</v>
<o n="." r="104"><o>__sys__t256</o><i>__sys__t253</i><i>__sys__t257</i></o>
<o n="+=" r="104"><o>percent</o><i>__sys__t256</i></o>
<v t="s" n="__sys__t261">.getHeroRecruitPercent.</v>
<o n="." r="106"><o>__sys__t260</o><i>numMgr</i><i>__sys__t261</i></o>
<o n="__sys__t260" r="106"><o>__sys__t263</o><i>numMgr</i><i>heroArr</i></o>
<o n="+=" r="106"><o>percent</o><i>__sys__t263</i></o>
<v t="s" n="__sys__t266">.unionID.</v>
<o n="." r="108"><o>__sys__t265</o><i>user</i><i>__sys__t266</i></o>
<o n="int" r="108"><o>__sys__t268</o><i>__sys__t265</i></o>
<o n="=" r="108"><o>unionID</o><i>__sys__t268</i></o>
<v t="s" n="__sys__t271">.getRichmanIDArr.</v>
<o n="." r="109"><o>__sys__t270</o><i>numMgr</i><i>__sys__t271</i></o>
<o n="__sys__t270" r="109"><o>__sys__t273</o><i>numMgr</i><i>unionID</i></o>
<o n="=" r="109"><o>richmanIDArr</o><i>__sys__t273</i></o>
<v t="s" n="__sys__t276">.getRichmanAddPercent.</v>
<o n="." r="110"><o>__sys__t275</o><i>numMgr</i><i>__sys__t276</i></o>
<o n="=" r="110"><o>type</o><i>__sys__t28</i></o>
<o n="__sys__t275" r="110"><o>__sys__t279</o><i>numMgr</i><i>richmanIDArr</i><i>type</i></o>
<o n="+=" r="110"><o>percent</o><i>__sys__t279</i></o>
<o n="*=" r="113"><o>point</o><i>percent</i></o>
<o n="floor" r="115"><o>__sys__t282</o><i>point</i></o>
<o n="+" r="115"><o>__sys__t283</o><i>__sys__t282</i><i>pointPlus</i></o>
<o n="=" r="115"><o>totalPoint</o><i>__sys__t283</i></o>
<v t="s" n="__sys__t286">.food.</v>
<o n="." r="117"><o>__sys__t285</o><i>user</i><i>__sys__t286</i></o>
<o n="number" r="117"><o>__sys__t288</o><i>__sys__t285</i></o>
<o n="=" r="117"><o>food</o><i>__sys__t288</i></o>
<o n=">" r="118"><o>__sys__t290</o><i>totalPoint</i><i>food</i></o>
<o n="="><o>__sys__rt</o><i>__sys__t290</i></o>
<o n="=="><o>__sys__t292</o><i>__sys__rt</i><i>__sys__t29</i></o>
<o n="if_goto"><o>__sys__t293</o><i>__sys__t292</i><i>__sys__t303</i></o>
<v t="s" n="__sys__t295">.sendMsg.</v>
<o n="." r="121"><o>__sys__t294</o><i>game</i><i>__sys__t295</i></o>
<o n="+" r="124"><o>__sys__t297</o><i>methodName</i><i>__sys__t30</i></o>
<o n=" -" r="124"><o>__sys__t298</o><i>__sys__t31</i></o>
<o n="arr" r="124"><o>__sys__t299</o><i>__sys__t297</i><i>__sys__t298</i></o>
<o n="__sys__t294" r="121"><o>__sys__t300</o><i>game</i><i>sessionID</i><i>__sys__t299</i></o>
<o n="return" r="126"><o>__sys__t301</o><i>__sys__t32</i></o>
<o n="goto"><o>__sys__t302</o><i>__sys__t304</i></o>
<v t="s" n="__sys__t306">.soldier.</v>
<o n="." r="128"><o>__sys__t305</o><i>user</i><i>__sys__t306</i></o>
<o n="number" r="128"><o>__sys__t308</o><i>__sys__t305</i></o>
<o n="=" r="128"><o>soldier</o><i>__sys__t308</i></o>
<o n="&lt;" r="131"><o>__sys__t310</o><i>charm</i><i>__sys__t33</i></o>
<o n="="><o>__sys__rt</o><i>__sys__t310</i></o>
<o n="=="><o>__sys__t312</o><i>__sys__rt</i><i>__sys__t34</i></o>
<o n="if_goto"><o>__sys__t313</o><i>__sys__t312</i><i>__sys__t316</i></o>
<o n="=" r="133"><o>dt</o><i>__sys__t35</i></o>
<o n="goto"><o>__sys__t315</o><i>__sys__t329</i></o>
<o n="&lt;" r="135"><o>__sys__t317</o><i>charm</i><i>__sys__t36</i></o>
<o n="="><o>__sys__rt</o><i>__sys__t317</i></o>
<o n="=="><o>__sys__t319</o><i>__sys__rt</i><i>__sys__t37</i></o>
<o n="if_goto"><o>__sys__t320</o><i>__sys__t319</i><i>__sys__t326</i></o>
<o n="*" r="137"><o>__sys__t321</o><i>__sys__t38</i><i>charm</i></o>
<o n="/" r="137"><o>__sys__t322</o><i>__sys__t321</i><i>__sys__t39</i></o>
<o n="floor" r="137"><o>__sys__t323</o><i>__sys__t322</i></o>
<o n="=" r="137"><o>dt</o><i>__sys__t323</i></o>
<o n="goto"><o>__sys__t325</o><i>__sys__t328</i></o>
<o n="=" r="141"><o>dt</o><i>__sys__t40</i></o>
<v t="s" n="__sys__t331">.soldier.</v>
<o n="." r="145"><o>__sys__t330</o><i>user</i><i>__sys__t331</i></o>
<o n="+" r="145"><o>__sys__t333</o><i>soldier</i><i>totalPoint</i></o>
<o n="=" r="145"><o>__sys__t330</o><i>__sys__t333</i></o>
<v t="s" n="__sys__t336">.food.</v>
<o n="." r="146"><o>__sys__t335</o><i>user</i><i>__sys__t336</i></o>
<o n="-" r="146"><o>__sys__t338</o><i>food</i><i>totalPoint</i></o>
<o n="=" r="146"><o>__sys__t335</o><i>__sys__t338</i></o>
<o n="=" r="147"><o>beginTime</o><i>newBeginTime</i></o>
<v t="s" n="__sys__t342">.dailyTask.</v>
<o n="." r="149"><o>__sys__t341</o><i>json</i><i>__sys__t342</i></o>
<v t="s" n="__sys__t345">.makeSoldierCount.</v>
<o n="." r="149"><o>__sys__t344</o><i>__sys__t341</i><i>__sys__t345</i></o>
<o n="ref" r="149"><o>__sys__t347</o><i>__sys__t344</i></o>
<o n="=" r="149"><o>makeSoldierCount</o><i>__sys__t347</i></o>
<o n="+=" r="150"><o>makeSoldierCount</o><i>__sys__t41</i></o>
<v t="s" n="__sys__t351">.achievement.</v>
<o n="." r="152"><o>__sys__t350</o><i>json</i><i>__sys__t351</i></o>
<v t="s" n="__sys__t354">.makeSoldier.</v>
<o n="." r="152"><o>__sys__t353</o><i>__sys__t350</i><i>__sys__t354</i></o>
<o n="ref" r="152"><o>__sys__t356</o><i>__sys__t353</i></o>
<o n="=" r="152"><o>makeSoldierAchievement</o><i>__sys__t356</i></o>
<o n="+=" r="153"><o>makeSoldierAchievement</o><i>__sys__t42</i></o>
<v t="s" n="__sys__t360">.limitTask.</v>
<o n="." r="155"><o>__sys__t359</o><i>json</i><i>__sys__t360</i></o>
<o n="=" r="155"><o>limitTask</o><i>__sys__t359</i></o>
<v t="s" n="__sys__t364">.activityMgr.</v>
<o n="." r="156"><o>__sys__t363</o><i>game</i><i>__sys__t364</i></o>
<o n="=" r="156"><o>activityMgr</o><i>__sys__t363</i></o>
<v t="s" n="__sys__t368">.updateLimitTask.</v>
<o n="." r="157"><o>__sys__t367</o><i>activityMgr</i><i>__sys__t368</i></o>
<o n="__sys__t367" r="157"><o>__sys__t370</o><i>activityMgr</i><i>limitTask</i></o>
<v t="s" n="__sys__t372">.makeSoldierCount.</v>
<o n="." r="158"><o>__sys__t371</o><i>limitTask</i><i>__sys__t372</i></o>
<o n="+=" r="158"><o>__sys__t371</o><i>__sys__t43</i></o>
<v t="s" n="__sys__t376">.json.</v>
<o n="." r="161"><o>__sys__t375</o><i>user</i><i>__sys__t376</i></o>
<o n="json_encode" r="161"><o>__sys__t378</o><i>json</i></o>
<o n="=" r="161"><o>__sys__t375</o><i>__sys__t378</i></o>
<v t="s" n="__sys__t381">.sendMsg.</v>
<o n="." r="163"><o>__sys__t380</o><i>game</i><i>__sys__t381</i></o>
<o n="+" r="166"><o>__sys__t383</o><i>methodName</i><i>__sys__t44</i></o>
<v t="s" n="__sys__t385">.makeSoldierCount.</v>
<o n="." r="166"><o>__sys__t384</o><i>limitTask</i><i>__sys__t385</i></o>
<o n="arr" r="166"><o>__sys__t387</o><i>__sys__t383</i><i>__sys__t45</i><i>makeSoldier</i><i>soldier</i><i>food</i><i>point</i><i>pointPlus</i><i>makeSoldierCount</i><i>makeSoldierAchievement</i><i>__sys__t384</i></o>
<o n="__sys__t380" r="163"><o>__sys__t388</o><i>game</i><i>sessionID</i><i>__sys__t387</i></o>
<o n="return" r="168"><o>__sys__t389</o><i>__sys__t46</i></o>
<o n="goto"><o>__sys__t390</o><i>__sys__t400</i></o>
<v t="s" n="__sys__t393">.sendMsg.</v>
<o n="." r="173"><o>__sys__t392</o><i>game</i><i>__sys__t393</i></o>
<o n="+" r="176"><o>__sys__t395</o><i>methodName</i><i>__sys__t47</i></o>
<o n=" -" r="176"><o>__sys__t396</o><i>__sys__t48</i></o>
<o n="arr" r="176"><o>__sys__t397</o><i>__sys__t395</i><i>__sys__t396</i></o>
<o n="__sys__t392" r="173"><o>__sys__t398</o><i>game</i><i>sessionID</i><i>__sys__t397</i></o>
<o n="return" r="178"><o>__sys__t399</o><i>__sys__t49</i></o>
<v n="__sys__rt" />
<v n="__sys__t101" />
<v n="__sys__t102" />
<v n="__sys__t104" />
<v n="__sys__t107" />
<v n="__sys__t108" />
<v n="__sys__t110" />
<v n="__sys__t112" />
<v n="__sys__t115" />
<v n="__sys__t117" />
<v n="__sys__t118" />
<v n="__sys__t120" />
<v n="__sys__t123" />
<v n="__sys__t124" />
<v n="__sys__t125" />
<v n="__sys__t127" />
<v n="__sys__t129" />
<v n="__sys__t130" />
<v n="__sys__t131" />
<v n="__sys__t135" />
<v n="__sys__t137" />
<v n="__sys__t140" />
<v n="__sys__t144" />
<v n="__sys__t146" />
<v n="__sys__t147" />
<v n="__sys__t148" />
<v n="__sys__t150" />
<v n="__sys__t152" />
<v n="__sys__t154" />
<v n="__sys__t155" />
<v n="__sys__t157" />
<v n="__sys__t160" />
<v n="__sys__t162" />
<v n="__sys__t164" />
<v n="__sys__t165" />
<v n="__sys__t166" />
<v n="__sys__t168" />
<v n="__sys__t169" />
<v n="__sys__t170" />
<v n="__sys__t173" />
<v n="__sys__t177" />
<v n="__sys__t182" />
<v n="__sys__t183" />
<v n="__sys__t184" />
<v n="__sys__t188" />
<v n="__sys__t191" />
<v n="__sys__t195" />
<v n="__sys__t199" />
<v n="__sys__t201" />
<v n="__sys__t207" />
<v n="__sys__t209" />
<v n="__sys__t210" />
<v n="__sys__t211" />
<v n="__sys__t213" />
<v n="__sys__t217" />
<v n="__sys__t219" />
<v n="__sys__t220" />
<v n="__sys__t221" />
<v n="__sys__t225" />
<v n="__sys__t227" />
<v n="__sys__t228" />
<v n="__sys__t229" />
<v n="__sys__t231" />
<v n="__sys__t233" />
<v n="__sys__t235" />
<v n="__sys__t237" />
<v n="__sys__t240" />
<v n="__sys__t241" />
<v n="__sys__t243" />
<v n="__sys__t246" />
<v n="__sys__t250" />
<v n="__sys__t253" />
<v n="__sys__t256" />
<v n="__sys__t260" />
<v n="__sys__t263" />
<v n="__sys__t265" />
<v n="__sys__t268" />
<v n="__sys__t270" />
<v n="__sys__t273" />
<v n="__sys__t275" />
<v n="__sys__t279" />
<v n="__sys__t282" />
<v n="__sys__t283" />
<v n="__sys__t285" />
<v n="__sys__t288" />
<v n="__sys__t290" />
<v n="__sys__t292" />
<v n="__sys__t293" />
<v n="__sys__t294" />
<v n="__sys__t297" />
<v n="__sys__t298" />
<v n="__sys__t299" />
<v n="__sys__t300" />
<v n="__sys__t301" />
<v n="__sys__t302" />
<v n="__sys__t305" />
<v n="__sys__t308" />
<v n="__sys__t310" />
<v n="__sys__t312" />
<v n="__sys__t313" />
<v n="__sys__t315" />
<v n="__sys__t317" />
<v n="__sys__t319" />
<v n="__sys__t320" />
<v n="__sys__t321" />
<v n="__sys__t322" />
<v n="__sys__t323" />
<v n="__sys__t325" />
<v n="__sys__t330" />
<v n="__sys__t333" />
<v n="__sys__t335" />
<v n="__sys__t338" />
<v n="__sys__t341" />
<v n="__sys__t344" />
<v n="__sys__t347" />
<v n="__sys__t350" />
<v n="__sys__t353" />
<v n="__sys__t356" />
<v n="__sys__t359" />
<v n="__sys__t363" />
<v n="__sys__t367" />
<v n="__sys__t370" />
<v n="__sys__t371" />
<v n="__sys__t375" />
<v n="__sys__t378" />
<v n="__sys__t380" />
<v n="__sys__t383" />
<v n="__sys__t384" />
<v n="__sys__t387" />
<v n="__sys__t388" />
<v n="__sys__t389" />
<v n="__sys__t390" />
<v n="__sys__t392" />
<v n="__sys__t395" />
<v n="__sys__t396" />
<v n="__sys__t397" />
<v n="__sys__t398" />
<v n="__sys__t399" />
<v n="__sys__t50" />
<v n="__sys__t52" />
<v n="__sys__t54" />
<v n="__sys__t56" />
<v n="__sys__t58" />
<v n="__sys__t61" />
<v n="__sys__t63" />
<v n="__sys__t66" />
<v n="__sys__t68" />
<v n="__sys__t71" />
<v n="__sys__t73" />
<v n="__sys__t76" />
<v n="__sys__t78" />
<v n="__sys__t82" />
<v n="__sys__t84" />
<v n="__sys__t87" />
<v n="__sys__t90" />
<v n="__sys__t93" />
<v n="__sys__t96" />
<v n="__sys__t98" />
<v n="activityMgr" />
<v n="beginTime" />
<v n="c" />
<v n="charm" />
<v n="curTime" />
<v n="dt" />
<v n="dt1000" />
<v n="endTime" />
<v n="food" />
<v n="game" />
<v n="heroArr" />
<v n="heroBeginTime" />
<v n="heroIndex" />
<v n="heroInfo" />
<v n="i" />
<v n="info" />
<v n="json" />
<v n="limitTask" />
<v n="makeSoldier" />
<v n="makeSoldierAchievement" />
<v n="makeSoldierCount" />
<v n="maxRecvCount" />
<v n="methodName" />
<v n="newBeginTime" />
<v n="newCurTime" />
<v n="numMgr" />
<v n="percent" />
<v n="point" />
<v n="pointPlus" />
<v n="recvCount" />
<v n="recvSign" />
<v n="remainingTime" />
<v n="richmanIDArr" />
<v n="roundBeginTime" />
<v n="roundEndTime" />
<v n="row" />
<v n="sessionID" />
<v n="soldier" />
<v n="totalPoint" />
<v n="type" />
<v n="unionID" />
<v n="useHeroArr" />
<v n="usePercent" />
<v n="useTime" />
<v n="user" />
</script>
