<?xml version="1.0" encoding="utf-8"?>
<script>
<v t="n" n="__sys__t301">167</v>
<v t="n" n="__sys__t298">165</v>
<v t="n" n="__sys__t297">165</v>
<v t="n" n="__sys__t280">151</v>
<v t="n" n="__sys__t266">142</v>
<v t="n" n="__sys__t263">140</v>
<v t="n" n="__sys__t262">140</v>
<v t="n" n="__sys__t233">118</v>
<v t="n" n="__sys__t52">16</v>
<v t="n" n="__sys__t51">16</v>
<v t="n" n="__sys__t1">0</v>
<v t="n" n="__sys__t2">1</v>
<v t="n" n="__sys__t3">2</v>
<v t="n" n="__sys__t4">3</v>
<v t="n" n="__sys__t5">0</v>
<v t="s" n="__sys__t6">.id.</v>
<v t="s" n="__sys__t7">.skill.</v>
<v t="s" n="__sys__t8">.,.</v>
<v t="s" n="__sys__t9">.id.</v>
<v t="s" n="__sys__t10">.Hero.</v>
<v t="n" n="__sys__t11">0</v>
<v t="s" n="__sys__t12">.name.</v>
<v t="s" n="__sys__t13">.specialty.</v>
<v t="s" n="__sys__t14">.head.</v>
<v t="s" n="__sys__t15">.level.</v>
<v t="s" n="__sys__t16">.promotion.</v>
<v t="s" n="__sys__t17">.strengthGrows.</v>
<v t="s" n="__sys__t18">.wisdomGrows.</v>
<v t="s" n="__sys__t19">.charmGrows.</v>
<v t="s" n="__sys__t20">.politicsGrows.</v>
<v t="s" n="__sys__t21">.strength.</v>
<v t="s" n="__sys__t22">.wisdom.</v>
<v t="s" n="__sys__t23">.charm.</v>
<v t="s" n="__sys__t24">.politics.</v>
<v t="n" n="__sys__t25">0</v>
<v t="n" n="__sys__t26">0</v>
<v t="s" n="__sys__t27">.id.</v>
<v t="s" n="__sys__t28">.heroID.</v>
<v t="n" n="__sys__t29">0</v>
<v t="n" n="__sys__t30">0</v>
<v t="n" n="__sys__t31">0</v>
<v t="n" n="__sys__t32">0</v>
<o n="input"><o>__sys__t33</o><i>__sys__t1</i></o>
<o n="="><o>self</o><i>__sys__t33</i></o>
<o n="input"><o>__sys__t35</o><i>__sys__t2</i></o>
<o n="="><o>heroID</o><i>__sys__t35</i></o>
<o n="input"><o>__sys__t37</o><i>__sys__t3</i></o>
<o n="="><o>heroArr</o><i>__sys__t37</i></o>
<o n="input"><o>__sys__t39</o><i>__sys__t4</i></o>
<o n="="><o>json</o><i>__sys__t39</i></o>
<v t="s" n="__sys__t42">.isHeroExistInHeroArr.</v>
<o n="." r="251"><o>__sys__t41</o><i>self</i><i>__sys__t42</i></o>
<o n="__sys__t41" r="251"><o>__sys__t44</o><i>self</i><i>heroID</i><i>heroArr</i></o>
<o n="="><o>__sys__rt</o><i>__sys__t44</i></o>
<o n="=="><o>__sys__t46</o><i>__sys__rt</i><i>__sys__t5</i></o>
<o n="if_goto"><o>__sys__t47</o><i>__sys__t46</i><i>__sys__t51</i></o>
<o n="handle" r="253"><o>__sys__t48</o></o>
<o n="return" r="253"><o>__sys__t49</o><i>__sys__t48</i></o>
<o n="goto"><o>__sys__t50</o><i>__sys__t52</i></o>
<v t="s" n="__sys__t54">.game.</v>
<o n="." r="256"><o>__sys__t53</o><i>self</i><i>__sys__t54</i></o>
<o n="=" r="256"><o>game</o><i>__sys__t53</i></o>
<v t="s" n="__sys__t58">.table.</v>
<o n="." r="257"><o>__sys__t57</o><i>game</i><i>__sys__t58</i></o>
<o n="=" r="257"><o>tableData</o><i>__sys__t57</i></o>
<v t="s" n="__sys__t62">.hero.</v>
<o n="." r="260"><o>__sys__t61</o><i>tableData</i><i>__sys__t62</i></o>
<v t="s" n="__sys__t65">.getRowFromColName.</v>
<o n="." r="260"><o>__sys__t64</o><i>__sys__t61</i><i>__sys__t65</i></o>
<o n="__sys__t64" r="260"><o>__sys__t67</o><i>__sys__t61</i><i>__sys__t6</i><i>heroID</i></o>
<o n="=" r="260"><o>info</o><i>__sys__t67</i></o>
<v t="s" n="__sys__t70">.getValFromColName.</v>
<o n="." r="261"><o>__sys__t69</o><i>info</i><i>__sys__t70</i></o>
<o n="__sys__t69" r="261"><o>__sys__t72</o><i>info</i><i>__sys__t7</i></o>
<o n="=" r="261"><o>skillStr</o><i>__sys__t72</i></o>
<o n="arr" r="262"><o>__sys__t74</o></o>
<o n="split" r="262"><o>__sys__t75</o><i>__sys__t74</i><i>skillStr</i><i>__sys__t8</i></o>
<o n="=" r="262"><o>skillArr</o><i>__sys__t75</i></o>
<v t="s" n="__sys__t78">.getValFromColName.</v>
<o n="." r="264"><o>__sys__t77</o><i>info</i><i>__sys__t78</i></o>
<o n="__sys__t77" r="264"><o>__sys__t80</o><i>info</i><i>__sys__t9</i></o>
<o n="=" r="264"><o>heroID</o><i>__sys__t80</i></o>
<v t="s" n="__sys__t83">.structMgr.</v>
<o n="." r="266"><o>__sys__t82</o><i>game</i><i>__sys__t83</i></o>
<o n="dict" r="266"><o>__sys__t85</o></o>
<o n="structMgr_upgradeObj" r="266"><o>__sys__t86</o><i>__sys__t82</i><i>__sys__t10</i><i>__sys__t85</i></o>
<o n="=" r="266"><o>hero</o><i>__sys__t86</i></o>
<o n="size" r="267"><o>__sys__t88</o><i>heroArr</i></o>
<o n="=" r="267"><o>heroIndex</o><i>__sys__t88</i></o>
<v t="s" n="__sys__t91">.heroIndex.</v>
<o n="." r="268"><o>__sys__t90</o><i>hero</i><i>__sys__t91</i></o>
<o n="=" r="268"><o>__sys__t90</o><i>heroIndex</i></o>
<v t="s" n="__sys__t95">.heroID.</v>
<o n="." r="269"><o>__sys__t94</o><i>hero</i><i>__sys__t95</i></o>
<o n="=" r="269"><o>__sys__t94</o><i>heroID</i></o>
<v t="s" n="__sys__t99">.useSign.</v>
<o n="." r="270"><o>__sys__t98</o><i>hero</i><i>__sys__t99</i></o>
<o n="=" r="270"><o>__sys__t98</o><i>__sys__t11</i></o>
<v t="s" n="__sys__t103">.name.</v>
<o n="." r="271"><o>__sys__t102</o><i>hero</i><i>__sys__t103</i></o>
<v t="s" n="__sys__t106">.getValFromColName.</v>
<o n="." r="271"><o>__sys__t105</o><i>info</i><i>__sys__t106</i></o>
<o n="__sys__t105" r="271"><o>__sys__t108</o><i>info</i><i>__sys__t12</i></o>
<o n="=" r="271"><o>__sys__t102</o><i>__sys__t108</i></o>
<v t="s" n="__sys__t111">.specialty.</v>
<o n="." r="272"><o>__sys__t110</o><i>hero</i><i>__sys__t111</i></o>
<v t="s" n="__sys__t114">.getValFromColName.</v>
<o n="." r="272"><o>__sys__t113</o><i>info</i><i>__sys__t114</i></o>
<o n="__sys__t113" r="272"><o>__sys__t116</o><i>info</i><i>__sys__t13</i></o>
<o n="=" r="272"><o>__sys__t110</o><i>__sys__t116</i></o>
<v t="s" n="__sys__t119">.head.</v>
<o n="." r="273"><o>__sys__t118</o><i>hero</i><i>__sys__t119</i></o>
<v t="s" n="__sys__t122">.getValFromColName.</v>
<o n="." r="273"><o>__sys__t121</o><i>info</i><i>__sys__t122</i></o>
<o n="__sys__t121" r="273"><o>__sys__t124</o><i>info</i><i>__sys__t14</i></o>
<o n="number" r="273"><o>__sys__t125</o><i>__sys__t124</i></o>
<o n="=" r="273"><o>__sys__t118</o><i>__sys__t125</i></o>
<v t="s" n="__sys__t128">.level.</v>
<o n="." r="274"><o>__sys__t127</o><i>hero</i><i>__sys__t128</i></o>
<v t="s" n="__sys__t131">.getValFromColName.</v>
<o n="." r="274"><o>__sys__t130</o><i>info</i><i>__sys__t131</i></o>
<o n="__sys__t130" r="274"><o>__sys__t133</o><i>info</i><i>__sys__t15</i></o>
<o n="number" r="274"><o>__sys__t134</o><i>__sys__t133</i></o>
<o n="=" r="274"><o>__sys__t127</o><i>__sys__t134</i></o>
<v t="s" n="__sys__t137">.promotion.</v>
<o n="." r="275"><o>__sys__t136</o><i>hero</i><i>__sys__t137</i></o>
<v t="s" n="__sys__t140">.getValFromColName.</v>
<o n="." r="275"><o>__sys__t139</o><i>info</i><i>__sys__t140</i></o>
<o n="__sys__t139" r="275"><o>__sys__t142</o><i>info</i><i>__sys__t16</i></o>
<o n="number" r="275"><o>__sys__t143</o><i>__sys__t142</i></o>
<o n="=" r="275"><o>__sys__t136</o><i>__sys__t143</i></o>
<v t="s" n="__sys__t146">.strengthGrows.</v>
<o n="." r="278"><o>__sys__t145</o><i>hero</i><i>__sys__t146</i></o>
<v t="s" n="__sys__t149">.getValFromColName.</v>
<o n="." r="278"><o>__sys__t148</o><i>info</i><i>__sys__t149</i></o>
<o n="__sys__t148" r="278"><o>__sys__t151</o><i>info</i><i>__sys__t17</i></o>
<o n="number" r="278"><o>__sys__t152</o><i>__sys__t151</i></o>
<o n="=" r="278"><o>__sys__t145</o><i>__sys__t152</i></o>
<v t="s" n="__sys__t155">.wisdomGrows.</v>
<o n="." r="279"><o>__sys__t154</o><i>hero</i><i>__sys__t155</i></o>
<v t="s" n="__sys__t158">.getValFromColName.</v>
<o n="." r="279"><o>__sys__t157</o><i>info</i><i>__sys__t158</i></o>
<o n="__sys__t157" r="279"><o>__sys__t160</o><i>info</i><i>__sys__t18</i></o>
<o n="number" r="279"><o>__sys__t161</o><i>__sys__t160</i></o>
<o n="=" r="279"><o>__sys__t154</o><i>__sys__t161</i></o>
<v t="s" n="__sys__t164">.charmGrows.</v>
<o n="." r="280"><o>__sys__t163</o><i>hero</i><i>__sys__t164</i></o>
<v t="s" n="__sys__t167">.getValFromColName.</v>
<o n="." r="280"><o>__sys__t166</o><i>info</i><i>__sys__t167</i></o>
<o n="__sys__t166" r="280"><o>__sys__t169</o><i>info</i><i>__sys__t19</i></o>
<o n="number" r="280"><o>__sys__t170</o><i>__sys__t169</i></o>
<o n="=" r="280"><o>__sys__t163</o><i>__sys__t170</i></o>
<v t="s" n="__sys__t173">.politicsGrows.</v>
<o n="." r="281"><o>__sys__t172</o><i>hero</i><i>__sys__t173</i></o>
<v t="s" n="__sys__t176">.getValFromColName.</v>
<o n="." r="281"><o>__sys__t175</o><i>info</i><i>__sys__t176</i></o>
<o n="__sys__t175" r="281"><o>__sys__t178</o><i>info</i><i>__sys__t20</i></o>
<o n="number" r="281"><o>__sys__t179</o><i>__sys__t178</i></o>
<o n="=" r="281"><o>__sys__t172</o><i>__sys__t179</i></o>
<v t="s" n="__sys__t182">.strength.</v>
<o n="." r="289"><o>__sys__t181</o><i>hero</i><i>__sys__t182</i></o>
<v t="s" n="__sys__t185">.getValFromColName.</v>
<o n="." r="289"><o>__sys__t184</o><i>info</i><i>__sys__t185</i></o>
<o n="__sys__t184" r="289"><o>__sys__t187</o><i>info</i><i>__sys__t21</i></o>
<o n="number" r="289"><o>__sys__t188</o><i>__sys__t187</i></o>
<o n="=" r="289"><o>__sys__t181</o><i>__sys__t188</i></o>
<v t="s" n="__sys__t191">.wisdom.</v>
<o n="." r="290"><o>__sys__t190</o><i>hero</i><i>__sys__t191</i></o>
<v t="s" n="__sys__t194">.getValFromColName.</v>
<o n="." r="290"><o>__sys__t193</o><i>info</i><i>__sys__t194</i></o>
<o n="__sys__t193" r="290"><o>__sys__t196</o><i>info</i><i>__sys__t22</i></o>
<o n="number" r="290"><o>__sys__t197</o><i>__sys__t196</i></o>
<o n="=" r="290"><o>__sys__t190</o><i>__sys__t197</i></o>
<v t="s" n="__sys__t200">.charm.</v>
<o n="." r="291"><o>__sys__t199</o><i>hero</i><i>__sys__t200</i></o>
<v t="s" n="__sys__t203">.getValFromColName.</v>
<o n="." r="291"><o>__sys__t202</o><i>info</i><i>__sys__t203</i></o>
<o n="__sys__t202" r="291"><o>__sys__t205</o><i>info</i><i>__sys__t23</i></o>
<o n="number" r="291"><o>__sys__t206</o><i>__sys__t205</i></o>
<o n="=" r="291"><o>__sys__t199</o><i>__sys__t206</i></o>
<v t="s" n="__sys__t209">.politics.</v>
<o n="." r="292"><o>__sys__t208</o><i>hero</i><i>__sys__t209</i></o>
<v t="s" n="__sys__t212">.getValFromColName.</v>
<o n="." r="292"><o>__sys__t211</o><i>info</i><i>__sys__t212</i></o>
<o n="__sys__t211" r="292"><o>__sys__t214</o><i>info</i><i>__sys__t24</i></o>
<o n="number" r="292"><o>__sys__t215</o><i>__sys__t214</i></o>
<o n="=" r="292"><o>__sys__t208</o><i>__sys__t215</i></o>
<v t="s" n="__sys__t218">.skill.</v>
<o n="." r="295"><o>__sys__t217</o><i>hero</i><i>__sys__t218</i></o>
<o n="=" r="295"><o>__sys__t217</o><i>skillArr</i></o>
<v t="s" n="__sys__t222">.treasure.</v>
<o n="." r="297"><o>__sys__t221</o><i>tableData</i><i>__sys__t222</i></o>
<o n="=" r="297"><o>treasureTable</o><i>__sys__t221</i></o>
<v t="s" n="__sys__t226">.size.</v>
<o n="." r="298"><o>__sys__t225</o><i>treasureTable</i><i>__sys__t226</i></o>
<o n="__sys__t225" r="298"><o>__sys__t228</o><i>treasureTable</i></o>
<o n="=" r="298"><o>treasureTCount</o><i>__sys__t228</i></o>
<o n="=" r="299"><o>i</o><i>__sys__t25</i></o>
<o n="dict" r="299"><o>__sys__t231</o></o>
<o n="=" r="299"><o>allGemIDMap</o><i>__sys__t231</i></o>
<o n="&lt;" r="300"><o>__sys__t234</o><i>i</i><i>treasureTCount</i></o>
<o n="="><o>__sys__rt</o><i>__sys__t234</i></o>
<o n="=="><o>__sys__t236</o><i>__sys__rt</i><i>__sys__t26</i></o>
<o n="if_goto"><o>__sys__t237</o><i>__sys__t236</i><i>__sys__t266</i></o>
<v t="s" n="__sys__t239">.getRow.</v>
<o n="." r="302"><o>__sys__t238</o><i>treasureTable</i><i>__sys__t239</i></o>
<o n="__sys__t238" r="302"><o>__sys__t241</o><i>treasureTable</i><i>i</i></o>
<o n="=" r="302"><o>rowT</o><i>__sys__t241</i></o>
<v t="s" n="__sys__t244">.getValFromColName.</v>
<o n="." r="303"><o>__sys__t243</o><i>rowT</i><i>__sys__t244</i></o>
<o n="__sys__t243" r="303"><o>__sys__t246</o><i>rowT</i><i>__sys__t27</i></o>
<o n="number" r="303"><o>__sys__t247</o><i>__sys__t246</i></o>
<o n="=" r="303"><o>gemID</o><i>__sys__t247</i></o>
<v t="s" n="__sys__t250">.getValFromColName.</v>
<o n="." r="304"><o>__sys__t249</o><i>rowT</i><i>__sys__t250</i></o>
<o n="__sys__t249" r="304"><o>__sys__t252</o><i>rowT</i><i>__sys__t28</i></o>
<o n="number" r="304"><o>__sys__t253</o><i>__sys__t252</i></o>
<o n="=" r="304"><o>heroIDS</o><i>__sys__t253</i></o>
<o n="==" r="305"><o>__sys__t255</o><i>heroIDS</i><i>heroID</i></o>
<o n="="><o>__sys__rt</o><i>__sys__t255</i></o>
<o n="=="><o>__sys__t257</o><i>__sys__rt</i><i>__sys__t29</i></o>
<o n="if_goto"><o>__sys__t258</o><i>__sys__t257</i><i>__sys__t262</i></o>
<o n="[]" r="307"><o>__sys__t259</o><i>allGemIDMap</i><i>gemID</i></o>
<o n="=" r="307"><o>__sys__t259</o><i>heroIDS</i></o>
<o n="goto"><o>__sys__t261</o><i>__sys__t263</i></o>
<o n="++" r="309"><o>i</o><i>i</i></o>
<o n="goto"><o>__sys__t265</o><i>__sys__t233</i></o>
<v t="s" n="__sys__t268">.gemSys.</v>
<o n="." r="311"><o>__sys__t267</o><i>json</i><i>__sys__t268</i></o>
<o n="=" r="311"><o>gemSys</o><i>__sys__t267</i></o>
<v t="s" n="__sys__t272">.gemArr.</v>
<o n="." r="312"><o>__sys__t271</o><i>gemSys</i><i>__sys__t272</i></o>
<o n="=" r="312"><o>gemArr</o><i>__sys__t271</i></o>
<o n="size" r="313"><o>__sys__t275</o><i>gemArr</i></o>
<o n="=" r="313"><o>gemArrCount</o><i>__sys__t275</i></o>
<o n="=" r="314"><o>k</o><i>__sys__t30</i></o>
<o n="arr" r="314"><o>__sys__t278</o></o>
<o n="=" r="314"><o>addHeroGemIndexArr</o><i>__sys__t278</i></o>
<o n="&lt;" r="315"><o>__sys__t281</o><i>k</i><i>gemArrCount</i></o>
<o n="="><o>__sys__rt</o><i>__sys__t281</i></o>
<o n="=="><o>__sys__t283</o><i>__sys__rt</i><i>__sys__t31</i></o>
<o n="if_goto"><o>__sys__t284</o><i>__sys__t283</i><i>__sys__t301</i></o>
<o n="[]" r="317"><o>__sys__t285</o><i>gemArr</i><i>k</i></o>
<o n="=" r="317"><o>gemInfo</o><i>__sys__t285</i></o>
<v t="s" n="__sys__t288">.id.</v>
<o n="." r="318"><o>__sys__t287</o><i>gemInfo</i><i>__sys__t288</i></o>
<o n="=" r="318"><o>gemID</o><i>__sys__t287</i></o>
<o n="exist" r="319"><o>__sys__t291</o><i>allGemIDMap</i><i>gemID</i></o>
<o n="="><o>__sys__rt</o><i>__sys__t291</i></o>
<o n="=="><o>__sys__t293</o><i>__sys__rt</i><i>__sys__t32</i></o>
<o n="if_goto"><o>__sys__t294</o><i>__sys__t293</i><i>__sys__t297</i></o>
<o n="push" r="321"><o>__sys__t295</o><i>addHeroGemIndexArr</i><i>k</i></o>
<o n="goto"><o>__sys__t296</o><i>__sys__t298</i></o>
<o n="++" r="323"><o>k</o><i>k</i></o>
<o n="goto"><o>__sys__t300</o><i>__sys__t280</i></o>
<v t="s" n="__sys__t303">.gemIndexArr.</v>
<o n="." r="325"><o>__sys__t302</o><i>hero</i><i>__sys__t303</i></o>
<o n="=" r="325"><o>__sys__t302</o><i>addHeroGemIndexArr</i></o>
<o n="push" r="328"><o>__sys__t306</o><i>heroArr</i><i>hero</i></o>
<o n="return" r="330"><o>__sys__t307</o><i>hero</i></o>
<v n="__sys__rt" />
<v n="__sys__t102" />
<v n="__sys__t105" />
<v n="__sys__t108" />
<v n="__sys__t110" />
<v n="__sys__t113" />
<v n="__sys__t116" />
<v n="__sys__t118" />
<v n="__sys__t121" />
<v n="__sys__t124" />
<v n="__sys__t125" />
<v n="__sys__t127" />
<v n="__sys__t130" />
<v n="__sys__t133" />
<v n="__sys__t134" />
<v n="__sys__t136" />
<v n="__sys__t139" />
<v n="__sys__t142" />
<v n="__sys__t143" />
<v n="__sys__t145" />
<v n="__sys__t148" />
<v n="__sys__t151" />
<v n="__sys__t152" />
<v n="__sys__t154" />
<v n="__sys__t157" />
<v n="__sys__t160" />
<v n="__sys__t161" />
<v n="__sys__t163" />
<v n="__sys__t166" />
<v n="__sys__t169" />
<v n="__sys__t170" />
<v n="__sys__t172" />
<v n="__sys__t175" />
<v n="__sys__t178" />
<v n="__sys__t179" />
<v n="__sys__t181" />
<v n="__sys__t184" />
<v n="__sys__t187" />
<v n="__sys__t188" />
<v n="__sys__t190" />
<v n="__sys__t193" />
<v n="__sys__t196" />
<v n="__sys__t197" />
<v n="__sys__t199" />
<v n="__sys__t202" />
<v n="__sys__t205" />
<v n="__sys__t206" />
<v n="__sys__t208" />
<v n="__sys__t211" />
<v n="__sys__t214" />
<v n="__sys__t215" />
<v n="__sys__t217" />
<v n="__sys__t221" />
<v n="__sys__t225" />
<v n="__sys__t228" />
<v n="__sys__t231" />
<v n="__sys__t234" />
<v n="__sys__t236" />
<v n="__sys__t237" />
<v n="__sys__t238" />
<v n="__sys__t241" />
<v n="__sys__t243" />
<v n="__sys__t246" />
<v n="__sys__t247" />
<v n="__sys__t249" />
<v n="__sys__t252" />
<v n="__sys__t253" />
<v n="__sys__t255" />
<v n="__sys__t257" />
<v n="__sys__t258" />
<v n="__sys__t259" />
<v n="__sys__t261" />
<v n="__sys__t265" />
<v n="__sys__t267" />
<v n="__sys__t271" />
<v n="__sys__t275" />
<v n="__sys__t278" />
<v n="__sys__t281" />
<v n="__sys__t283" />
<v n="__sys__t284" />
<v n="__sys__t285" />
<v n="__sys__t287" />
<v n="__sys__t291" />
<v n="__sys__t293" />
<v n="__sys__t294" />
<v n="__sys__t295" />
<v n="__sys__t296" />
<v n="__sys__t300" />
<v n="__sys__t302" />
<v n="__sys__t306" />
<v n="__sys__t307" />
<v n="__sys__t33" />
<v n="__sys__t35" />
<v n="__sys__t37" />
<v n="__sys__t39" />
<v n="__sys__t41" />
<v n="__sys__t44" />
<v n="__sys__t46" />
<v n="__sys__t47" />
<v n="__sys__t48" />
<v n="__sys__t49" />
<v n="__sys__t50" />
<v n="__sys__t53" />
<v n="__sys__t57" />
<v n="__sys__t61" />
<v n="__sys__t64" />
<v n="__sys__t67" />
<v n="__sys__t69" />
<v n="__sys__t72" />
<v n="__sys__t74" />
<v n="__sys__t75" />
<v n="__sys__t77" />
<v n="__sys__t80" />
<v n="__sys__t82" />
<v n="__sys__t85" />
<v n="__sys__t86" />
<v n="__sys__t88" />
<v n="__sys__t90" />
<v n="__sys__t94" />
<v n="__sys__t98" />
<v n="addHeroGemIndexArr" />
<v n="allGemIDMap" />
<v n="game" />
<v n="gemArr" />
<v n="gemArrCount" />
<v n="gemID" />
<v n="gemInfo" />
<v n="gemSys" />
<v n="hero" />
<v n="heroArr" />
<v n="heroID" />
<v n="heroIDS" />
<v n="heroIndex" />
<v n="i" />
<v n="info" />
<v n="json" />
<v n="k" />
<v n="rowT" />
<v n="self" />
<v n="skillArr" />
<v n="skillStr" />
<v n="tableData" />
<v n="treasureTCount" />
<v n="treasureTable" />
</script>
