<?xml version="1.0" encoding="utf-8"?>
<script>
<v t="n" n="__sys__t366">208</v>
<v t="n" n="__sys__t365">208</v>
<v t="n" n="__sys__t364">208</v>
<v t="n" n="__sys__t358">205</v>
<v t="n" n="__sys__t357">205</v>
<v t="n" n="__sys__t347">198</v>
<v t="n" n="__sys__t346">198</v>
<v t="n" n="__sys__t317">176</v>
<v t="n" n="__sys__t283">155</v>
<v t="n" n="__sys__t282">155</v>
<v t="n" n="__sys__t280">154</v>
<v t="n" n="__sys__t279">154</v>
<v t="n" n="__sys__t229">123</v>
<v t="n" n="__sys__t228">123</v>
<v t="n" n="__sys__t220">116</v>
<v t="n" n="__sys__t219">116</v>
<v t="n" n="__sys__t162">72</v>
<v t="n" n="__sys__t161">72</v>
<v t="n" n="__sys__t118">44</v>
<v t="n" n="__sys__t117">44</v>
<v t="n" n="__sys__t1">0</v>
<v t="n" n="__sys__t2">1</v>
<v t="s" n="__sys__t3">.methodName.</v>
<v t="s" n="__sys__t4">.sessionID.</v>
<v t="s" n="__sys__t5">.updateGlobal_var.</v>
<v t="s" n="__sys__t6">.heroIndex.</v>
<v t="s" n="__sys__t7">.userID.</v>
<v t="s" n="__sys__t8">.tmpArr.</v>
<v t="s" n="__sys__t9">.tmpArr2.</v>
<v t="s" n="__sys__t10">.tmpDict.</v>
<v t="s" n="__sys__t11">.tmpDict2.</v>
<v t="n" n="__sys__t12">0</v>
<v t="s" n="__sys__t13">.Result.</v>
<v t="n" n="__sys__t14">4</v>
<v t="n" n="__sys__t15">0</v>
<v t="n" n="__sys__t16">0</v>
<v t="s" n="__sys__t17">.Result.</v>
<v t="n" n="__sys__t18">5</v>
<v t="n" n="__sys__t19">0</v>
<v t="n" n="__sys__t20">1</v>
<v t="s" n="__sys__t21">. .</v>
<v t="n" n="__sys__t22">0</v>
<v t="n" n="__sys__t23">0</v>
<v t="s" n="__sys__t24">. .</v>
<v t="s" n="__sys__t25">.bt2.</v>
<v t="s" n="__sys__t26">. .</v>
<v t="s" n="__sys__t27">.dt2.</v>
<v t="n" n="__sys__t28">0</v>
<v t="s" n="__sys__t29">.Result.</v>
<v t="n" n="__sys__t30">2</v>
<v t="n" n="__sys__t31">0</v>
<v t="n" n="__sys__t32">0</v>
<v t="n" n="__sys__t33">0</v>
<v t="s" n="__sys__t34">..</v>
<v t="s" n="__sys__t35">..</v>
<v t="n" n="__sys__t36">0</v>
<v t="n" n="__sys__t37">0</v>
<v t="s" n="__sys__t38">.union.</v>
<v t="s" n="__sys__t39">.id.</v>
<v t="s" n="__sys__t40">.*.</v>
<v t="n" n="__sys__t41">1000</v>
<v t="n" n="__sys__t42">0</v>
<v t="n" n="__sys__t43">0</v>
<v t="n" n="__sys__t44">3</v>
<v t="n" n="__sys__t45">0</v>
<v t="s" n="__sys__t46">.Result.</v>
<v t="n" n="__sys__t47">3</v>
<v t="n" n="__sys__t48">0</v>
<v t="n" n="__sys__t49">0</v>
<v t="n" n="__sys__t50">2</v>
<v t="n" n="__sys__t51">0</v>
<v t="s" n="__sys__t52">.lastHitReward.</v>
<v t="n" n="__sys__t53">0</v>
<v t="n" n="__sys__t54">0</v>
<v t="n" n="__sys__t55">35</v>
<v t="n" n="__sys__t56">0</v>
<v t="n" n="__sys__t57">1</v>
<v t="n" n="__sys__t58">0</v>
<v t="n" n="__sys__t59">0</v>
<v t="n" n="__sys__t60">1</v>
<v t="n" n="__sys__t61">8</v>
<v t="n" n="__sys__t62">2</v>
<v t="n" n="__sys__t63">2</v>
<v t="n" n="__sys__t64">1</v>
<o n="input"><o>__sys__t65</o><i>__sys__t1</i></o>
<o n="="><o>user</o><i>__sys__t65</i></o>
<o n="input"><o>__sys__t67</o><i>__sys__t2</i></o>
<o n="="><o>game</o><i>__sys__t67</i></o>
<o n="link" r="149"><o>__sys__t69</o><i>__sys__t3</i></o>
<o n="=" r="149"><o>methodName</o><i>__sys__t69</i></o>
<o n="link" r="149"><o>__sys__t71</o><i>__sys__t4</i></o>
<o n="=" r="149"><o>sessionID</o><i>__sys__t71</i></o>
<o n="link" r="149"><o>__sys__t73</o><i>__sys__t5</i></o>
<o n="=" r="149"><o>updateGlobal_var</o><i>__sys__t73</i></o>
<o n="link" r="149"><o>__sys__t75</o><i>__sys__t6</i></o>
<o n="=" r="149"><o>heroIndex</o><i>__sys__t75</i></o>
<o n="link" r="149"><o>__sys__t77</o><i>__sys__t7</i></o>
<o n="=" r="149"><o>userID</o><i>__sys__t77</i></o>
<o n="link" r="149"><o>__sys__t79</o><i>__sys__t8</i></o>
<o n="=" r="149"><o>tmpArr</o><i>__sys__t79</i></o>
<o n="link" r="149"><o>__sys__t81</o><i>__sys__t9</i></o>
<o n="=" r="149"><o>tmpArr2</o><i>__sys__t81</i></o>
<o n="link" r="149"><o>__sys__t83</o><i>__sys__t10</i></o>
<o n="=" r="149"><o>tmpDict</o><i>__sys__t83</i></o>
<o n="link" r="149"><o>__sys__t85</o><i>__sys__t11</i></o>
<o n="=" r="149"><o>tmpDict2</o><i>__sys__t85</i></o>
<v t="s" n="__sys__t88">.json.</v>
<o n="." r="151"><o>__sys__t87</o><i>user</i><i>__sys__t88</i></o>
<o n="json_decode" r="151"><o>__sys__t90</o><i>__sys__t87</i></o>
<o n="=" r="151"><o>json</o><i>__sys__t90</i></o>
<v t="s" n="__sys__t93">.hero.</v>
<o n="." r="152"><o>__sys__t92</o><i>json</i><i>__sys__t93</i></o>
<o n="ref" r="152"><o>__sys__t95</o><i>__sys__t92</i></o>
<o n="=" r="152"><o>heroArr</o><i>__sys__t95</i></o>
<o n="[]" r="153"><o>__sys__t97</o><i>heroArr</i><i>heroIndex</i></o>
<o n="=" r="153"><o>heroInfo</o><i>__sys__t97</i></o>
<v t="s" n="__sys__t100">.gold2.</v>
<o n="." r="154"><o>__sys__t99</o><i>user</i><i>__sys__t100</i></o>
<o n="number" r="154"><o>__sys__t102</o><i>__sys__t99</i></o>
<o n="=" r="154"><o>gold2</o><i>__sys__t102</i></o>
<o n="empty" r="156"><o>__sys__t104</o><i>heroInfo</i></o>
<o n="="><o>__sys__rt</o><i>__sys__t104</i></o>
<o n="=="><o>__sys__t106</o><i>__sys__rt</i><i>__sys__t12</i></o>
<o n="if_goto"><o>__sys__t107</o><i>__sys__t106</i><i>__sys__t117</i></o>
<v t="s" n="__sys__t109">.sendMsg.</v>
<o n="." r="159"><o>__sys__t108</o><i>game</i><i>__sys__t109</i></o>
<o n="+" r="162"><o>__sys__t111</o><i>methodName</i><i>__sys__t13</i></o>
<o n=" -" r="162"><o>__sys__t112</o><i>__sys__t14</i></o>
<o n="arr" r="162"><o>__sys__t113</o><i>__sys__t111</i><i>__sys__t112</i></o>
<o n="__sys__t108" r="159"><o>__sys__t114</o><i>game</i><i>sessionID</i><i>__sys__t113</i></o>
<o n="return" r="164"><o>__sys__t115</o><i>__sys__t15</i></o>
<o n="goto"><o>__sys__t116</o><i>__sys__t118</i></o>
<v t="s" n="__sys__t120">.jsonExt.</v>
<o n="." r="168"><o>__sys__t119</o><i>user</i><i>__sys__t120</i></o>
<o n="json_decode" r="168"><o>__sys__t122</o><i>__sys__t119</i></o>
<o n="=" r="168"><o>jsonExt</o><i>__sys__t122</i></o>
<v t="s" n="__sys__t125">.worldBoss.</v>
<o n="." r="169"><o>__sys__t124</o><i>jsonExt</i><i>__sys__t125</i></o>
<o n="=" r="169"><o>worldBoss</o><i>__sys__t124</i></o>
<v t="s" n="__sys__t129">.bossHeroMap.</v>
<o n="." r="170"><o>__sys__t128</o><i>worldBoss</i><i>__sys__t129</i></o>
<o n="ref" r="170"><o>__sys__t131</o><i>__sys__t128</i></o>
<o n="=" r="170"><o>bossHeroMap</o><i>__sys__t131</i></o>
<v t="s" n="__sys__t134">.bossHeroRecoveMap.</v>
<o n="." r="171"><o>__sys__t133</o><i>worldBoss</i><i>__sys__t134</i></o>
<o n="ref" r="171"><o>__sys__t136</o><i>__sys__t133</i></o>
<o n="=" r="171"><o>bossHeroRecoveMap</o><i>__sys__t136</i></o>
<v t="s" n="__sys__t139">.worldBossHurtDate.</v>
<o n="." r="173"><o>__sys__t138</o><i>user</i><i>__sys__t139</i></o>
<o n="ref" r="173"><o>__sys__t141</o><i>__sys__t138</i></o>
<o n="=" r="173"><o>worldBossHurtDate</o><i>__sys__t141</i></o>
<v t="s" n="__sys__t144">.worldBossHurt.</v>
<o n="." r="174"><o>__sys__t143</o><i>user</i><i>__sys__t144</i></o>
<o n="ref" r="174"><o>__sys__t146</o><i>__sys__t143</i></o>
<o n="=" r="174"><o>worldBossHurt</o><i>__sys__t146</i></o>
<o n="exist" r="176"><o>__sys__t148</o><i>bossHeroMap</i><i>heroIndex</i></o>
<o n="="><o>__sys__rt</o><i>__sys__t148</i></o>
<o n="=="><o>__sys__t150</o><i>__sys__rt</i><i>__sys__t16</i></o>
<o n="if_goto"><o>__sys__t151</o><i>__sys__t150</i><i>__sys__t161</i></o>
<v t="s" n="__sys__t153">.sendMsg.</v>
<o n="." r="179"><o>__sys__t152</o><i>game</i><i>__sys__t153</i></o>
<o n="+" r="182"><o>__sys__t155</o><i>methodName</i><i>__sys__t17</i></o>
<o n=" -" r="182"><o>__sys__t156</o><i>__sys__t18</i></o>
<o n="arr" r="182"><o>__sys__t157</o><i>__sys__t155</i><i>__sys__t156</i></o>
<o n="__sys__t152" r="179"><o>__sys__t158</o><i>game</i><i>sessionID</i><i>__sys__t157</i></o>
<o n="return" r="184"><o>__sys__t159</o><i>__sys__t19</i></o>
<o n="goto"><o>__sys__t160</o><i>__sys__t162</i></o>
<o n="push" r="186"><o>__sys__t163</o><i>bossHeroMap</i><i>heroIndex</i><i>__sys__t20</i></o>
<o n="now" r="189"><o>__sys__t164</o></o>
<o n="=" r="189"><o>nowTime</o><i>__sys__t164</i></o>
<o n="strtotime" r="190"><o>__sys__t166</o><i>nowTime</i></o>
<o n="=" r="190"><o>currentTime</o><i>__sys__t166</i></o>
<o n="arr" r="191"><o>__sys__t168</o></o>
<o n="split" r="191"><o>__sys__t169</o><i>__sys__t168</i><i>nowTime</i><i>__sys__t21</i></o>
<o n="=" r="191"><o>t</o><i>__sys__t169</i></o>
<o n="[]" r="192"><o>__sys__t171</o><i>t</i><i>__sys__t22</i></o>
<o n="=" r="192"><o>t_a</o><i>__sys__t171</i></o>
<v t="s" n="__sys__t174">.table.</v>
<o n="." r="194"><o>__sys__t173</o><i>game</i><i>__sys__t174</i></o>
<v t="s" n="__sys__t177">.worldBoss.</v>
<o n="." r="194"><o>__sys__t176</o><i>__sys__t173</i><i>__sys__t177</i></o>
<v t="s" n="__sys__t180">.getRow.</v>
<o n="." r="194"><o>__sys__t179</o><i>__sys__t176</i><i>__sys__t180</i></o>
<o n="__sys__t179" r="194"><o>__sys__t182</o><i>__sys__t176</i><i>__sys__t23</i></o>
<o n="=" r="194"><o>rowWB</o><i>__sys__t182</i></o>
<v t="s" n="__sys__t185">.getValFromColName.</v>
<o n="." r="195"><o>__sys__t184</o><i>rowWB</i><i>__sys__t185</i></o>
<o n="__sys__t184" r="195"><o>__sys__t187</o><i>rowWB</i><i>__sys__t25</i></o>
<o n="+" r="195"><o>__sys__t188</o><i>t_a</i><i>__sys__t24</i></o>
<o n="+" r="195"><o>__sys__t189</o><i>__sys__t188</i><i>__sys__t187</i></o>
<o n="strtotime" r="195"><o>__sys__t190</o><i>__sys__t189</i></o>
<o n="=" r="195"><o>startTime</o><i>__sys__t190</i></o>
<v t="s" n="__sys__t193">.getValFromColName.</v>
<o n="." r="197"><o>__sys__t192</o><i>rowWB</i><i>__sys__t193</i></o>
<o n="__sys__t192" r="197"><o>__sys__t195</o><i>rowWB</i><i>__sys__t27</i></o>
<o n="+" r="197"><o>__sys__t196</o><i>t_a</i><i>__sys__t26</i></o>
<o n="+" r="197"><o>__sys__t197</o><i>__sys__t196</i><i>__sys__t195</i></o>
<o n="strtotime" r="197"><o>__sys__t198</o><i>__sys__t197</i></o>
<o n="=" r="197"><o>endTime</o><i>__sys__t198</i></o>
<o n="number" r="200"><o>__sys__t200</o><i>currentTime</i></o>
<o n="number" r="200"><o>__sys__t201</o><i>startTime</i></o>
<o n="number" r="200"><o>__sys__t202</o><i>currentTime</i></o>
<o n="number" r="200"><o>__sys__t203</o><i>endTime</i></o>
<o n="&lt;" r="200"><o>__sys__t204</o><i>__sys__t200</i><i>__sys__t201</i></o>
<o n=">" r="200"><o>__sys__t205</o><i>__sys__t202</i><i>__sys__t203</i></o>
<o n="||" r="200"><o>__sys__t206</o><i>__sys__t204</i><i>__sys__t205</i></o>
<o n="="><o>__sys__rt</o><i>__sys__t206</i></o>
<o n="=="><o>__sys__t208</o><i>__sys__rt</i><i>__sys__t28</i></o>
<o n="if_goto"><o>__sys__t209</o><i>__sys__t208</i><i>__sys__t219</i></o>
<v t="s" n="__sys__t211">.sendMsg.</v>
<o n="." r="203"><o>__sys__t210</o><i>game</i><i>__sys__t211</i></o>
<o n="+" r="206"><o>__sys__t213</o><i>methodName</i><i>__sys__t29</i></o>
<o n=" -" r="206"><o>__sys__t214</o><i>__sys__t30</i></o>
<o n="arr" r="206"><o>__sys__t215</o><i>__sys__t213</i><i>__sys__t214</i></o>
<o n="__sys__t210" r="203"><o>__sys__t216</o><i>game</i><i>sessionID</i><i>__sys__t215</i></o>
<o n="return" r="208"><o>__sys__t217</o><i>__sys__t31</i></o>
<o n="goto"><o>__sys__t218</o><i>__sys__t220</i></o>
<o n="!=" r="211"><o>__sys__t221</o><i>worldBossHurtDate</i><i>t_a</i></o>
<o n="="><o>__sys__rt</o><i>__sys__t221</i></o>
<o n="=="><o>__sys__t223</o><i>__sys__rt</i><i>__sys__t32</i></o>
<o n="if_goto"><o>__sys__t224</o><i>__sys__t223</i><i>__sys__t228</i></o>
<o n="=" r="213"><o>worldBossHurtDate</o><i>t_a</i></o>
<o n="=" r="214"><o>worldBossHurt</o><i>__sys__t33</i></o>
<o n="goto"><o>__sys__t227</o><i>__sys__t229</i></o>
<v t="s" n="__sys__t231">.numMgr.</v>
<o n="." r="218"><o>__sys__t230</o><i>game</i><i>__sys__t231</i></o>
<v t="s" n="__sys__t234">.getHeroAttack.</v>
<o n="." r="218"><o>__sys__t233</o><i>__sys__t230</i><i>__sys__t234</i></o>
<o n="__sys__t233" r="218"><o>__sys__t236</o><i>__sys__t230</i><i>heroInfo</i><i>json</i></o>
<o n="=" r="218"><o>damage</o><i>__sys__t236</i></o>
<v t="s" n="__sys__t239">.worldBossScoreTotal.</v>
<o n="." r="221"><o>__sys__t238</o><i>user</i><i>__sys__t239</i></o>
<o n="ref" r="221"><o>__sys__t241</o><i>__sys__t238</i></o>
<o n="=" r="221"><o>worldBossScoreTotal</o><i>__sys__t241</i></o>
<v t="s" n="__sys__t244">.worldBossScore.</v>
<o n="." r="222"><o>__sys__t243</o><i>user</i><i>__sys__t244</i></o>
<o n="ref" r="222"><o>__sys__t246</o><i>__sys__t243</i></o>
<o n="=" r="222"><o>worldBossScore</o><i>__sys__t246</i></o>
<v t="s" n="__sys__t249">.unionID.</v>
<o n="." r="223"><o>__sys__t248</o><i>user</i><i>__sys__t249</i></o>
<o n="=" r="223"><o>unionID</o><i>__sys__t248</i></o>
<o n="=" r="224"><o>unionName</o><i>__sys__t34</i></o>
<o n="=" r="225"><o>myUnionName</o><i>__sys__t35</i></o>
<o n="!=" r="226"><o>__sys__t254</o><i>unionID</i><i>__sys__t36</i></o>
<o n="="><o>__sys__rt</o><i>__sys__t254</i></o>
<o n="=="><o>__sys__t256</o><i>__sys__rt</i><i>__sys__t37</i></o>
<o n="if_goto"><o>__sys__t257</o><i>__sys__t256</i><i>__sys__t282</i></o>
<v t="s" n="__sys__t259">.rd.</v>
<o n="." r="228"><o>__sys__t258</o><i>game</i><i>__sys__t259</i></o>
<v t="s" n="__sys__t262">.getRow.</v>
<o n="." r="228"><o>__sys__t261</o><i>__sys__t258</i><i>__sys__t262</i></o>
<v t="s" n="__sys__t265">.cnn.</v>
<o n="." r="228"><o>__sys__t264</o><i>game</i><i>__sys__t265</i></o>
<o n="__sys__t261" r="228"><o>__sys__t267</o><i>__sys__t258</i><i>__sys__t264</i><i>__sys__t38</i><i>__sys__t39</i><i>unionID</i><i>__sys__t40</i><i>__sys__t41</i></o>
<o n="=" r="228"><o>unionRow</o><i>__sys__t267</i></o>
<o n="empty" r="229"><o>__sys__t269</o><i>unionRow</i></o>
<o n="!" r="229"><o>__sys__t270</o><i>__sys__t269</i></o>
<o n="="><o>__sys__rt</o><i>__sys__t270</i></o>
<o n="=="><o>__sys__t272</o><i>__sys__rt</i><i>__sys__t42</i></o>
<o n="if_goto"><o>__sys__t273</o><i>__sys__t272</i><i>__sys__t279</i></o>
<v t="s" n="__sys__t275">.name.</v>
<o n="." r="231"><o>__sys__t274</o><i>unionRow</i><i>__sys__t275</i></o>
<o n="=" r="231"><o>myUnionName</o><i>__sys__t274</i></o>
<o n="goto"><o>__sys__t278</o><i>__sys__t280</i></o>
<o n="goto"><o>__sys__t281</o><i>__sys__t283</i></o>
<v t="s" n="__sys__t285">.nickname.</v>
<o n="." r="235"><o>__sys__t284</o><i>user</i><i>__sys__t285</i></o>
<v t="s" n="__sys__t288">.head.</v>
<o n="." r="235"><o>__sys__t287</o><i>user</i><i>__sys__t288</i></o>
<v t="s" n="__sys__t291">.level.</v>
<o n="." r="235"><o>__sys__t290</o><i>user</i><i>__sys__t291</i></o>
<v t="s" n="__sys__t294">.fashionID.</v>
<o n="." r="235"><o>__sys__t293</o><i>user</i><i>__sys__t294</i></o>
<o n="updateGlobal_var" r="235"><o>__sys__t296</o><i>game</i><i>t_a</i><i>damage</i><i>userID</i><i>__sys__t284</i><i>__sys__t287</i><i>__sys__t290</i><i>myUnionName</i><i>__sys__t293</i></o>
<o n="=" r="235"><o>backArr</o><i>__sys__t296</i></o>
<v t="s" n="__sys__t299">.limitTask.</v>
<o n="." r="237"><o>__sys__t298</o><i>json</i><i>__sys__t299</i></o>
<o n="=" r="237"><o>limitTask</o><i>__sys__t298</i></o>
<o n="[]" r="238"><o>__sys__t302</o><i>backArr</i><i>__sys__t43</i></o>
<o n=" -" r="238"><o>__sys__t303</o><i>__sys__t44</i></o>
<o n="==" r="238"><o>__sys__t304</o><i>__sys__t302</i><i>__sys__t303</i></o>
<o n="="><o>__sys__rt</o><i>__sys__t304</i></o>
<o n="=="><o>__sys__t306</o><i>__sys__rt</i><i>__sys__t45</i></o>
<o n="if_goto"><o>__sys__t307</o><i>__sys__t306</i><i>__sys__t317</i></o>
<v t="s" n="__sys__t309">.sendMsg.</v>
<o n="." r="241"><o>__sys__t308</o><i>game</i><i>__sys__t309</i></o>
<o n="+" r="244"><o>__sys__t311</o><i>methodName</i><i>__sys__t46</i></o>
<o n=" -" r="244"><o>__sys__t312</o><i>__sys__t47</i></o>
<o n="arr" r="244"><o>__sys__t313</o><i>__sys__t311</i><i>__sys__t312</i></o>
<o n="__sys__t308" r="241"><o>__sys__t314</o><i>game</i><i>sessionID</i><i>__sys__t313</i></o>
<o n="return" r="246"><o>__sys__t315</o><i>__sys__t48</i></o>
<o n="goto"><o>__sys__t316</o><i>__sys__t366</i></o>
<o n="[]" r="248"><o>__sys__t318</o><i>backArr</i><i>__sys__t49</i></o>
<o n="==" r="248"><o>__sys__t319</o><i>__sys__t318</i><i>__sys__t50</i></o>
<o n="="><o>__sys__rt</o><i>__sys__t319</i></o>
<o n="=="><o>__sys__t321</o><i>__sys__rt</i><i>__sys__t51</i></o>
<o n="if_goto"><o>__sys__t322</o><i>__sys__t321</i><i>__sys__t364</i></o>
<v t="s" n="__sys__t324">.getValFromColName.</v>
<o n="." r="250"><o>__sys__t323</o><i>rowWB</i><i>__sys__t324</i></o>
<o n="__sys__t323" r="250"><o>__sys__t326</o><i>rowWB</i><i>__sys__t52</i></o>
<o n="number" r="250"><o>__sys__t327</o><i>__sys__t326</i></o>
<o n="=" r="250"><o>lastHitReward</o><i>__sys__t327</i></o>
<o n="+=" r="251"><o>gold2</o><i>lastHitReward</i></o>
<o n=">" r="252"><o>__sys__t330</o><i>lastHitReward</i><i>__sys__t53</i></o>
<o n="="><o>__sys__rt</o><i>__sys__t330</i></o>
<o n="=="><o>__sys__t332</o><i>__sys__rt</i><i>__sys__t54</i></o>
<o n="if_goto"><o>__sys__t333</o><i>__sys__t332</i><i>__sys__t346</i></o>
<v t="s" n="__sys__t335">.gold.</v>
<o n="." r="254"><o>__sys__t334</o><i>user</i><i>__sys__t335</i></o>
<o n="number" r="254"><o>__sys__t337</o><i>__sys__t334</i></o>
<o n="number" r="254"><o>__sys__t338</o><i>gold2</i></o>
<o n="+" r="254"><o>__sys__t339</o><i>__sys__t337</i><i>__sys__t338</i></o>
<o n="=" r="254"><o>allGold</o><i>__sys__t339</i></o>
<v t="s" n="__sys__t342">.saveResIO.</v>
<o n="." r="255"><o>__sys__t341</o><i>game</i><i>__sys__t342</i></o>
<o n="__sys__t341" r="255"><o>__sys__t344</o><i>game</i><i>userID</i><i>__sys__t55</i><i>__sys__t56</i><i>__sys__t57</i><i>lastHitReward</i><i>allGold</i></o>
<o n="goto"><o>__sys__t345</o><i>__sys__t347</i></o>
<o n="!=" r="257"><o>__sys__t348</o><i>gold2</i><i>__sys__t58</i></o>
<o n="="><o>__sys__rt</o><i>__sys__t348</i></o>
<o n="=="><o>__sys__t350</o><i>__sys__rt</i><i>__sys__t59</i></o>
<o n="if_goto"><o>__sys__t351</o><i>__sys__t350</i><i>__sys__t357</i></o>
<v t="s" n="__sys__t353">.gold2.</v>
<o n="." r="259"><o>__sys__t352</o><i>user</i><i>__sys__t353</i></o>
<o n="=" r="259"><o>__sys__t352</o><i>gold2</i></o>
<o n="goto"><o>__sys__t356</o><i>__sys__t358</i></o>
<v t="s" n="__sys__t360">.killWorldBoss.</v>
<o n="." r="263"><o>__sys__t359</o><i>limitTask</i><i>__sys__t360</i></o>
<o n="+=" r="263"><o>__sys__t359</o><i>__sys__t60</i></o>
<o n="goto"><o>__sys__t363</o><i>__sys__t365</i></o>
<o n="[]" r="269"><o>__sys__t367</o><i>backArr</i><i>__sys__t61</i></o>
<o n="number" r="269"><o>__sys__t368</o><i>worldBossHurt</i></o>
<o n="+" r="269"><o>__sys__t369</o><i>__sys__t368</i><i>__sys__t367</i></o>
<o n="=" r="269"><o>worldBossHurt</o><i>__sys__t369</i></o>
<o n="[]" r="270"><o>__sys__t371</o><i>backArr</i><i>__sys__t62</i></o>
<o n="number" r="270"><o>__sys__t372</o><i>worldBossScoreTotal</i></o>
<o n="+" r="270"><o>__sys__t373</o><i>__sys__t372</i><i>__sys__t371</i></o>
<o n="=" r="270"><o>worldBossScoreTotal</o><i>__sys__t373</i></o>
<o n="[]" r="271"><o>__sys__t375</o><i>backArr</i><i>__sys__t63</i></o>
<o n="number" r="271"><o>__sys__t376</o><i>worldBossScore</i></o>
<o n="+" r="271"><o>__sys__t377</o><i>__sys__t376</i><i>__sys__t375</i></o>
<o n="=" r="271"><o>worldBossScore</o><i>__sys__t377</i></o>
<v t="s" n="__sys__t380">.json.</v>
<o n="." r="276"><o>__sys__t379</o><i>user</i><i>__sys__t380</i></o>
<o n="json_encode" r="276"><o>__sys__t382</o><i>json</i></o>
<o n="=" r="276"><o>__sys__t379</o><i>__sys__t382</i></o>
<v t="s" n="__sys__t385">.jsonExt.</v>
<o n="." r="277"><o>__sys__t384</o><i>user</i><i>__sys__t385</i></o>
<o n="json_encode" r="277"><o>__sys__t387</o><i>jsonExt</i></o>
<o n="=" r="277"><o>__sys__t384</o><i>__sys__t387</i></o>
<o n="=" r="279"><o>tmpArr</o><i>backArr</i></o>
<o n="=" r="280"><o>tmpDict</o><i>bossHeroMap</i></o>
<o n="=" r="281"><o>tmpDict2</o><i>bossHeroRecoveMap</i></o>
<o n="push" r="282"><o>__sys__t392</o><i>tmpArr2</i><i>worldBossHurt</i></o>
<o n="push" r="283"><o>__sys__t393</o><i>tmpArr2</i><i>worldBossScoreTotal</i></o>
<o n="push" r="284"><o>__sys__t394</o><i>tmpArr2</i><i>worldBossScore</i></o>
<o n="push" r="285"><o>__sys__t395</o><i>tmpArr2</i><i>gold2</i></o>
<v t="s" n="__sys__t397">.killWorldBoss.</v>
<o n="." r="286"><o>__sys__t396</o><i>limitTask</i><i>__sys__t397</i></o>
<o n="push" r="286"><o>__sys__t399</o><i>tmpArr2</i><i>__sys__t396</i></o>
<o n="return" r="288"><o>__sys__t400</o><i>__sys__t64</i></o>
<v n="__sys__rt" />
<v n="__sys__t102" />
<v n="__sys__t104" />
<v n="__sys__t106" />
<v n="__sys__t107" />
<v n="__sys__t108" />
<v n="__sys__t111" />
<v n="__sys__t112" />
<v n="__sys__t113" />
<v n="__sys__t114" />
<v n="__sys__t115" />
<v n="__sys__t116" />
<v n="__sys__t119" />
<v n="__sys__t122" />
<v n="__sys__t124" />
<v n="__sys__t128" />
<v n="__sys__t131" />
<v n="__sys__t133" />
<v n="__sys__t136" />
<v n="__sys__t138" />
<v n="__sys__t141" />
<v n="__sys__t143" />
<v n="__sys__t146" />
<v n="__sys__t148" />
<v n="__sys__t150" />
<v n="__sys__t151" />
<v n="__sys__t152" />
<v n="__sys__t155" />
<v n="__sys__t156" />
<v n="__sys__t157" />
<v n="__sys__t158" />
<v n="__sys__t159" />
<v n="__sys__t160" />
<v n="__sys__t163" />
<v n="__sys__t164" />
<v n="__sys__t166" />
<v n="__sys__t168" />
<v n="__sys__t169" />
<v n="__sys__t171" />
<v n="__sys__t173" />
<v n="__sys__t176" />
<v n="__sys__t179" />
<v n="__sys__t182" />
<v n="__sys__t184" />
<v n="__sys__t187" />
<v n="__sys__t188" />
<v n="__sys__t189" />
<v n="__sys__t190" />
<v n="__sys__t192" />
<v n="__sys__t195" />
<v n="__sys__t196" />
<v n="__sys__t197" />
<v n="__sys__t198" />
<v n="__sys__t200" />
<v n="__sys__t201" />
<v n="__sys__t202" />
<v n="__sys__t203" />
<v n="__sys__t204" />
<v n="__sys__t205" />
<v n="__sys__t206" />
<v n="__sys__t208" />
<v n="__sys__t209" />
<v n="__sys__t210" />
<v n="__sys__t213" />
<v n="__sys__t214" />
<v n="__sys__t215" />
<v n="__sys__t216" />
<v n="__sys__t217" />
<v n="__sys__t218" />
<v n="__sys__t221" />
<v n="__sys__t223" />
<v n="__sys__t224" />
<v n="__sys__t227" />
<v n="__sys__t230" />
<v n="__sys__t233" />
<v n="__sys__t236" />
<v n="__sys__t238" />
<v n="__sys__t241" />
<v n="__sys__t243" />
<v n="__sys__t246" />
<v n="__sys__t248" />
<v n="__sys__t254" />
<v n="__sys__t256" />
<v n="__sys__t257" />
<v n="__sys__t258" />
<v n="__sys__t261" />
<v n="__sys__t264" />
<v n="__sys__t267" />
<v n="__sys__t269" />
<v n="__sys__t270" />
<v n="__sys__t272" />
<v n="__sys__t273" />
<v n="__sys__t274" />
<v n="__sys__t278" />
<v n="__sys__t281" />
<v n="__sys__t284" />
<v n="__sys__t287" />
<v n="__sys__t290" />
<v n="__sys__t293" />
<v n="__sys__t296" />
<v n="__sys__t298" />
<v n="__sys__t302" />
<v n="__sys__t303" />
<v n="__sys__t304" />
<v n="__sys__t306" />
<v n="__sys__t307" />
<v n="__sys__t308" />
<v n="__sys__t311" />
<v n="__sys__t312" />
<v n="__sys__t313" />
<v n="__sys__t314" />
<v n="__sys__t315" />
<v n="__sys__t316" />
<v n="__sys__t318" />
<v n="__sys__t319" />
<v n="__sys__t321" />
<v n="__sys__t322" />
<v n="__sys__t323" />
<v n="__sys__t326" />
<v n="__sys__t327" />
<v n="__sys__t330" />
<v n="__sys__t332" />
<v n="__sys__t333" />
<v n="__sys__t334" />
<v n="__sys__t337" />
<v n="__sys__t338" />
<v n="__sys__t339" />
<v n="__sys__t341" />
<v n="__sys__t344" />
<v n="__sys__t345" />
<v n="__sys__t348" />
<v n="__sys__t350" />
<v n="__sys__t351" />
<v n="__sys__t352" />
<v n="__sys__t356" />
<v n="__sys__t359" />
<v n="__sys__t363" />
<v n="__sys__t367" />
<v n="__sys__t368" />
<v n="__sys__t369" />
<v n="__sys__t371" />
<v n="__sys__t372" />
<v n="__sys__t373" />
<v n="__sys__t375" />
<v n="__sys__t376" />
<v n="__sys__t377" />
<v n="__sys__t379" />
<v n="__sys__t382" />
<v n="__sys__t384" />
<v n="__sys__t387" />
<v n="__sys__t392" />
<v n="__sys__t393" />
<v n="__sys__t394" />
<v n="__sys__t395" />
<v n="__sys__t396" />
<v n="__sys__t399" />
<v n="__sys__t400" />
<v n="__sys__t65" />
<v n="__sys__t67" />
<v n="__sys__t69" />
<v n="__sys__t71" />
<v n="__sys__t73" />
<v n="__sys__t75" />
<v n="__sys__t77" />
<v n="__sys__t79" />
<v n="__sys__t81" />
<v n="__sys__t83" />
<v n="__sys__t85" />
<v n="__sys__t87" />
<v n="__sys__t90" />
<v n="__sys__t92" />
<v n="__sys__t95" />
<v n="__sys__t97" />
<v n="__sys__t99" />
<v n="allGold" />
<v n="backArr" />
<v n="bossHeroMap" />
<v n="bossHeroRecoveMap" />
<v n="currentTime" />
<v n="damage" />
<v n="endTime" />
<v n="game" />
<v n="gold2" />
<v n="heroArr" />
<v n="heroIndex" />
<v n="heroInfo" />
<v n="json" />
<v n="jsonExt" />
<v n="lastHitReward" />
<v n="limitTask" />
<v n="methodName" />
<v n="myUnionName" />
<v n="nowTime" />
<v n="rowWB" />
<v n="sessionID" />
<v n="startTime" />
<v n="t" />
<v n="t_a" />
<v n="tmpArr" />
<v n="tmpArr2" />
<v n="tmpDict" />
<v n="tmpDict2" />
<v n="unionID" />
<v n="unionName" />
<v n="unionRow" />
<v n="updateGlobal_var" />
<v n="user" />
<v n="userID" />
<v n="worldBoss" />
<v n="worldBossHurt" />
<v n="worldBossHurtDate" />
<v n="worldBossScore" />
<v n="worldBossScoreTotal" />
</script>
